EDAhelper/EDAhelper.py
EDAhelper/__init__.py
EDAhelper/column_stats.py
EDAhelper/numeric_plots.py
EDAhelper/plot_histogram.py
edahelper-3.1.7.dist-info/LICENSE
edahelper-3.1.7.dist-info/WHEEL
edahelper-3.1.7.dist-info/METADATA
edahelper-3.1.7.dist-info/RECORD
