Metadata-Version: 2.1
Name: edahelper
Version: 3.1.7
Summary: Toolset to make EDA easier!
Home-page: https://github.com/UBC-MDS/EDAhelper.git
License: MIT
Author: Rowan Sivanandam, Steven Leung, Vera Cui, Jennifer Hoang
Requires-Python: >=3.8,<4.0
Classifier: License :: OSI Approved :: MIT License
Classifier: Programming Language :: Python :: 3
Classifier: Programming Language :: Python :: 3.10
Classifier: Programming Language :: Python :: 3.8
Classifier: Programming Language :: Python :: 3.9
Requires-Dist: altair (>=4.2.0,<5.0.0)
Project-URL: Documentation, https://edahelper.readthedocs.io
Project-URL: Repository, https://github.com/UBC-MDS/EDAhelper.git
